{"cameraMode":{"drawMode":0,"name":"Shaded","section":"Shading Mode"},"sceneLighting":false,"audioPlay":false,"sceneViewState":{"m_AlwaysRefresh":false,"showFog":true,"showSkybox":false,"showFlares":true,"showImageEffects":true,"showParticleSystems":true,"showVisualEffectGraphs":true,"m_FxEnabled":true},"in2DMode":false,"pivot":{"x":4.873020172119141,"y":3.3504626750946047,"z":-257.6723327636719},"rotation":{"x":-0.2354210764169693,"y":-0.17754144966602326,"z":0.04383908957242966,"w":-0.9545642137527466},"size":8.060532569885254,"orthographic":false}